llm_cost/__init__.py
llm_cost/background.py
llm_cost/context.py
llm_cost/extractors.py
llm_cost/idempotency.py
llm_cost/openrouter_pricing.py
llm_cost/pricing.py
llm_cost/sinks.py
orchestra_llm_cost-0.1.4.dist-info/licenses/LICENSE
orchestra_llm_cost-0.1.4.dist-info/METADATA
orchestra_llm_cost-0.1.4.dist-info/WHEEL
orchestra_llm_cost-0.1.4.dist-info/top_level.txt
orchestra_llm_cost-0.1.4.dist-info/RECORD
