Metadata-Version: 2.4
Name: orchestra-llm-cost
Version: 0.1.4
Summary: Plug-and-play LLM token/cost tracking SDK with multiple sinks and audit metadata
Author-email: Orchestra <team@orchestra.space>
License-Expression: MIT
Project-URL: Homepage, https://github.com/orchestra-ai/llm-cost
Project-URL: Repository, https://github.com/orchestra-ai/llm-cost
Keywords: llm,pricing,tokens,billing,supabase,openai,cost-tracking
Classifier: Development Status :: 4 - Beta
Classifier: Intended Audience :: Developers
Classifier: Programming Language :: Python :: 3
Classifier: Programming Language :: Python :: 3.9
Classifier: Programming Language :: Python :: 3.10
Classifier: Programming Language :: Python :: 3.11
Classifier: Programming Language :: Python :: 3.12
Classifier: Operating System :: OS Independent
Classifier: Topic :: Software Development :: Libraries :: Python Modules
Requires-Python: >=3.9
License-File: LICENSE
Requires-Dist: httpx>=0.27.0
Requires-Dist: supabase>=2.4.0
Dynamic: license-file
